LICENSE
iterdir/__init__.py
iterdir/__main__.py
iterdir/py.typed
iterdir-0.0.9.dist-info/LICENSE
iterdir-0.0.9.dist-info/METADATA
iterdir-0.0.9.dist-info/WHEEL
iterdir-0.0.9.dist-info/entry_points.txt
iterdir-0.0.9.dist-info/RECORD
